{
  "latest_round": 897,
  "next_round": 898,
  "hot_cold": {
    "hot": [
      [
        39,
        15
      ],
      [
        17,
        11
      ],
      [
        43,
        11
      ],
      [
        22,
        9
      ],
      [
        26,
        9
      ],
      [
        28,
        9
      ],
      [
        32,
        9
      ],
      [
        34,
        9
      ],
      [
        38,
        9
      ],
      [
        18,
        8
      ]
    ],
    "cold": [
      [
        11,
        3
      ],
      [
        7,
        4
      ],
      [
        20,
        4
      ],
      [
        21,
        4
      ],
      [
        29,
        4
      ],
      [
        35,
        4
      ],
      [
        5,
        5
      ],
      [
        6,
        5
      ],
      [
        8,
        5
      ],
      [
        9,
        5
      ]
    ],
    "overdue": [
      [
        21,
        2.763157894736842
      ],
      [
        30,
        2.7278989667049367
      ],
      [
        11,
        2.6274285714285712
      ],
      [
        10,
        2.542141230068337
      ],
      [
        2,
        2.5086107921928815
      ],
      [
        20,
        2.3228803716608595
      ],
      [
        35,
        2.2369337979094075
      ],
      [
        33,
        1.9682539682539681
      ],
      [
        44,
        1.8602520045819015
      ],
      [
        24,
        1.5954545454545455
      ]
    ]
  },
  "engine_predictions": {
    "advancedpattern": [
      6,
      7,
      12,
      22,
      26,
      36
    ],
    "gap": [
      1,
      7,
      13,
      19,
      25,
      31
    ],
    "graph": [
      8,
      11,
      14,
      34,
      43,
      45
    ],
    "lstm": [
      12,
      26,
      31,
      38,
      39,
      41
    ],
    "ml": [
      6,
      7,
      13,
      26,
      31,
      44
    ],
    "numerology": [
      17,
      23,
      24,
      25,
      26,
      31
    ],
    "pattern": [
      3,
      13,
      15,
      23,
      33,
      43
    ],
    "sequencecorrelation": [
      3,
      16,
      19,
      34,
      36,
      43
    ],
    "statistical": [
      2,
      10,
      21,
      30,
      33,
      44
    ],
    "timeseries": [
      2,
      3,
      9,
      14,
      27,
      31
    ]
  },
  "predicted_sets": [
    {
      "numbers": [
        3,
        7,
        12,
        26,
        31,
        44
      ],
      "confidence": 72.66666666666666
    },
    {
      "numbers": [
        7,
        19,
        26,
        31,
        33,
        44
      ],
      "confidence": 72.0
    },
    {
      "numbers": [
        7,
        13,
        14,
        25,
        31,
        36
      ],
      "confidence": 70.63333333333333
    },
    {
      "numbers": [
        12,
        13,
        26,
        27,
        31,
        43
      ],
      "confidence": 70.42500000000001
    },
    {
      "numbers": [
        2,
        13,
        23,
        25,
        26,
        31
      ],
      "confidence": 70.42500000000001
    },
    {
      "numbers": [
        7,
        19,
        23,
        26,
        31,
        36
      ],
      "confidence": 70.42500000000001
    },
    {
      "numbers": [
        2,
        13,
        22,
        26,
        31,
        43
      ],
      "confidence": 70.25
    },
    {
      "numbers": [
        3,
        13,
        26,
        31,
        34,
        36
      ],
      "confidence": 70.21666666666667
    },
    {
      "numbers": [
        2,
        12,
        25,
        26,
        31,
        34
      ],
      "confidence": 69.75833333333334
    },
    {
      "numbers": [
        3,
        12,
        26,
        27,
        31,
        33
      ],
      "confidence": 69.75833333333334
    },
    {
      "numbers": [
        3,
        13,
        25,
        31,
        34,
        36
      ],
      "confidence": 69.75833333333334
    },
    {
      "numbers": [
        3,
        7,
        26,
        27,
        31,
        34
      ],
      "confidence": 69.725
    },
    {
      "numbers": [
        7,
        12,
        13,
        22,
        31,
        43
      ],
      "confidence": 69.58333333333334
    },
    {
      "numbers": [
        2,
        6,
        13,
        26,
        31,
        33
      ],
      "confidence": 69.55
    },
    {
      "numbers": [
        3,
        6,
        26,
        31,
        36,
        44
      ],
      "confidence": 69.55
    },
    {
      "numbers": [
        2,
        6,
        7,
        31,
        33,
        44
      ],
      "confidence": 69.26666666666668
    },
    {
      "numbers": [
        2,
        12,
        19,
        23,
        31,
        44
      ],
      "confidence": 69.125
    },
    {
      "numbers": [
        7,
        12,
        25,
        26,
        36,
        44
      ],
      "confidence": 69.125
    },
    {
      "numbers": [
        6,
        14,
        23,
        27,
        31,
        43
      ],
      "confidence": 69.125
    },
    {
      "numbers": [
        6,
        12,
        26,
        27,
        31,
        33
      ],
      "confidence": 69.09166666666667
    },
    {
      "numbers": [
        13,
        19,
        23,
        31,
        36,
        44
      ],
      "confidence": 69.09166666666667
    },
    {
      "numbers": [
        12,
        13,
        14,
        19,
        31,
        43
      ],
      "confidence": 69.05833333333334
    },
    {
      "numbers": [
        2,
        14,
        27,
        31,
        33,
        36
      ],
      "confidence": 68.63333333333333
    },
    {
      "numbers": [
        7,
        11,
        12,
        26,
        34,
        44
      ],
      "confidence": 68.45833333333334
    },
    {
      "numbers": [
        3,
        7,
        13,
        22,
        36,
        44
      ],
      "confidence": 68.45833333333334
    },
    {
      "numbers": [
        7,
        11,
        26,
        33,
        34,
        44
      ],
      "confidence": 68.45833333333334
    },
    {
      "numbers": [
        3,
        12,
        27,
        31,
        33,
        36
      ],
      "confidence": 68.42500000000001
    },
    {
      "numbers": [
        2,
        6,
        14,
        23,
        31,
        34
      ],
      "confidence": 68.42500000000001
    },
    {
      "numbers": [
        7,
        13,
        14,
        22,
        26,
        34
      ],
      "confidence": 68.42500000000001
    },
    {
      "numbers": [
        3,
        6,
        22,
        31,
        33,
        44
      ],
      "confidence": 68.42500000000001
    },
    {
      "numbers": [
        6,
        13,
        22,
        31,
        33,
        34
      ],
      "confidence": 68.42500000000001
    },
    {
      "numbers": [
        6,
        7,
        19,
        23,
        26,
        34
      ],
      "confidence": 68.42500000000001
    },
    {
      "numbers": [
        7,
        12,
        14,
        27,
        31,
        33
      ],
      "confidence": 68.42500000000001
    },
    {
      "numbers": [
        6,
        7,
        14,
        31,
        33,
        36
      ],
      "confidence": 68.39166666666668
    },
    {
      "numbers": [
        12,
        14,
        22,
        25,
        26,
        31
      ],
      "confidence": 68.39166666666668
    },
    {
      "numbers": [
        6,
        7,
        12,
        19,
        31,
        36
      ],
      "confidence": 68.39166666666668
    },
    {
      "numbers": [
        6,
        7,
        14,
        22,
        25,
        31
      ],
      "confidence": 68.2290034051216
    },
    {
      "numbers": [
        6,
        13,
        14,
        23,
        31,
        36
      ],
      "confidence": 68.21666666666667
    },
    {
      "numbers": [
        3,
        12,
        23,
        26,
        43,
        44
      ],
      "confidence": 68.21666666666667
    },
    {
      "numbers": [
        6,
        7,
        22,
        26,
        31,
        36
      ],
      "confidence": 68.18333333333334
    },
    {
      "numbers": [
        6,
        7,
        19,
        23,
        25,
        44
      ],
      "confidence": 67.96666666666667
    },
    {
      "numbers": [
        7,
        12,
        13,
        22,
        36,
        44
      ],
      "confidence": 67.79166666666666
    },
    {
      "numbers": [
        7,
        12,
        19,
        34,
        43,
        44
      ],
      "confidence": 67.75833333333334
    },
    {
      "numbers": [
        2,
        3,
        12,
        26,
        27,
        44
      ],
      "confidence": 67.75833333333334
    },
    {
      "numbers": [
        3,
        11,
        14,
        25,
        26,
        36
      ],
      "confidence": 67.75833333333334
    },
    {
      "numbers": [
        2,
        14,
        25,
        27,
        31,
        34
      ],
      "confidence": 67.75833333333334
    },
    {
      "numbers": [
        6,
        12,
        22,
        23,
        25,
        31
      ],
      "confidence": 67.75833333333334
    },
    {
      "numbers": [
        2,
        22,
        25,
        26,
        34,
        43
      ],
      "confidence": 67.75833333333334
    },
    {
      "numbers": [
        13,
        14,
        27,
        31,
        33,
        36
      ],
      "confidence": 67.725
    },
    {
      "numbers": [
        7,
        13,
        27,
        34,
        36,
        43
      ],
      "confidence": 67.58333333333334
    },
    {
      "numbers": [
        3,
        13,
        26,
        27,
        34,
        36
      ],
      "confidence": 67.55
    },
    {
      "numbers": [
        7,
        14,
        19,
        26,
        34,
        36
      ],
      "confidence": 67.55
    },
    {
      "numbers": [
        2,
        7,
        12,
        13,
        26,
        44
      ],
      "confidence": 67.52067007178829
    },
    {
      "numbers": [
        7,
        11,
        12,
        13,
        26,
        34
      ],
      "confidence": 67.2290034051216
    },
    {
      "numbers": [
        13,
        14,
        19,
        22,
        36,
        43
      ],
      "confidence": 67.09166666666667
    },
    {
      "numbers": [
        3,
        12,
        14,
        19,
        36,
        44
      ],
      "confidence": 67.09166666666667
    },
    {
      "numbers": [
        7,
        13,
        14,
        22,
        23,
        36
      ],
      "confidence": 67.09166666666667
    },
    {
      "numbers": [
        2,
        12,
        19,
        25,
        43,
        44
      ],
      "confidence": 67.09166666666667
    },
    {
      "numbers": [
        2,
        23,
        26,
        27,
        36,
        44
      ],
      "confidence": 67.09166666666667
    },
    {
      "numbers": [
        11,
        19,
        23,
        31,
        34,
        36
      ],
      "confidence": 67.05833333333334
    },
    {
      "numbers": [
        6,
        22,
        25,
        31,
        33,
        36
      ],
      "confidence": 67.05833333333334
    },
    {
      "numbers": [
        11,
        13,
        14,
        22,
        26,
        43
      ],
      "confidence": 67.05833333333334
    },
    {
      "numbers": [
        3,
        7,
        12,
        22,
        34,
        44
      ],
      "confidence": 66.91666666666666
    },
    {
      "numbers": [
        2,
        13,
        23,
        27,
        36,
        43
      ],
      "confidence": 66.91666666666666
    },
    {
      "numbers": [
        3,
        7,
        12,
        27,
        34,
        44
      ],
      "confidence": 66.91666666666666
    },
    {
      "numbers": [
        3,
        6,
        19,
        26,
        27,
        36
      ],
      "confidence": 66.88333333333333
    },
    {
      "numbers": [
        2,
        13,
        33,
        34,
        36,
        43
      ],
      "confidence": 66.88333333333333
    },
    {
      "numbers": [
        3,
        7,
        23,
        26,
        27,
        44
      ],
      "confidence": 66.85
    },
    {
      "numbers": [
        7,
        11,
        19,
        22,
        23,
        36
      ],
      "confidence": 66.63333333333333
    },
    {
      "numbers": [
        2,
        11,
        19,
        33,
        36,
        44
      ],
      "confidence": 66.63333333333333
    },
    {
      "numbers": [
        7,
        11,
        12,
        14,
        33,
        36
      ],
      "confidence": 66.6
    },
    {
      "numbers": [
        2,
        11,
        12,
        27,
        36,
        43
      ],
      "confidence": 66.45833333333334
    },
    {
      "numbers": [
        3,
        11,
        12,
        23,
        34,
        36
      ],
      "confidence": 66.42500000000001
    },
    {
      "numbers": [
        2,
        22,
        25,
        34,
        36,
        43
      ],
      "confidence": 66.42500000000001
    },
    {
      "numbers": [
        2,
        13,
        14,
        27,
        34,
        44
      ],
      "confidence": 66.25
    },
    {
      "numbers": [
        7,
        23,
        25,
        33,
        34,
        44
      ],
      "confidence": 66.21666666666667
    },
    {
      "numbers": [
        3,
        6,
        27,
        33,
        43,
        44
      ],
      "confidence": 66.21666666666667
    },
    {
      "numbers": [
        12,
        13,
        22,
        25,
        36,
        43
      ],
      "confidence": 66.21666666666667
    },
    {
      "numbers": [
        12,
        22,
        26,
        27,
        33,
        43
      ],
      "confidence": 66.21666666666667
    },
    {
      "numbers": [
        7,
        11,
        13,
        14,
        33,
        44
      ],
      "confidence": 66.21666666666667
    },
    {
      "numbers": [
        3,
        6,
        22,
        23,
        34,
        43
      ],
      "confidence": 66.21666666666667
    },
    {
      "numbers": [
        2,
        12,
        25,
        26,
        27,
        36
      ],
      "confidence": 66.21666666666667
    },
    {
      "numbers": [
        2,
        11,
        23,
        26,
        33,
        36
      ],
      "confidence": 66.21666666666667
    },
    {
      "numbers": [
        12,
        13,
        26,
        27,
        33,
        36
      ],
      "confidence": 66.18333333333334
    },
    {
      "numbers": [
        6,
        11,
        13,
        14,
        26,
        31
      ],
      "confidence": 65.81233673845495
    },
    {
      "numbers": [
        3,
        11,
        22,
        23,
        25,
        44
      ],
      "confidence": 65.75833333333334
    },
    {
      "numbers": [
        7,
        11,
        12,
        19,
        27,
        36
      ],
      "confidence": 65.75833333333334
    },
    {
      "numbers": [
        6,
        11,
        12,
        14,
        22,
        43
      ],
      "confidence": 65.75833333333334
    },
    {
      "numbers": [
        2,
        3,
        6,
        22,
        33,
        44
      ],
      "confidence": 65.55
    },
    {
      "numbers": [
        3,
        12,
        23,
        27,
        33,
        34
      ],
      "confidence": 65.55
    },
    {
      "numbers": [
        7,
        12,
        14,
        22,
        23,
        34
      ],
      "confidence": 65.55
    },
    {
      "numbers": [
        2,
        6,
        13,
        33,
        34,
        36
      ],
      "confidence": 65.51666666666667
    },
    {
      "numbers": [
        11,
        12,
        22,
        23,
        36,
        44
      ],
      "confidence": 65.09166666666667
    },
    {
      "numbers": [
        6,
        12,
        13,
        22,
        26,
        27
      ],
      "confidence": 64.94567007178827
    },
    {
      "numbers": [
        2,
        12,
        14,
        23,
        25,
        26
      ],
      "confidence": 64.48733673845496
    },
    {
      "numbers": [
        2,
        6,
        19,
        22,
        27,
        36
      ],
      "confidence": 64.21666666666667
    },
    {
      "numbers": [
        11,
        14,
        23,
        27,
        34,
        44
      ],
      "confidence": 64.21666666666667
    },
    {
      "numbers": [
        3,
        11,
        12,
        19,
        22,
        36
      ],
      "confidence": 63.687336738454945
    },
    {
      "numbers": [
        6,
        11,
        12,
        14,
        23,
        36
      ],
      "confidence": 63.187336738454945
    },
    {
      "numbers": [
        6,
        7,
        13,
        22,
        26,
        27
      ],
      "confidence": 63.11233673845494
    }
  ],
  "sum_range": [
    107,
    169
  ],
  "export_time": 1769672236.7450988
}